[{ "id": "BB5F2AAC5986479E92D874DBC27DE295", "parent" : "#", "text": "cerrar sesion", "a_attr": {"href": "#", "data-related": "[]"} },{ "id": "933C53E698824D2C8CC4DBD8F3CB9C07", "parent" : "#", "text": "horario", "a_attr": {"href": "Movimientoporlosmenus.html", "data-related": "[]"} },{ "id": "194B577E57CA42528CB0FBCC35FD8A93", "parent" : "#", "text": "Iniciar sesion", "a_attr": {"href": "IniciarsesionoRegistrarse.html", "data-related": "[{\"title\":\"Iniciar sesion o Registrarse\",\"url\":\"IniciarsesionoRegistrarse.html\"},{\"title\":\"Movimiento por los menus\",\"url\":\"Movimientoporlosmenus.html\"}]"} },{ "id": "AC130710D952472E8BFF418F5DB9488D", "parent" : "#", "text": "linea", "a_attr": {"href": "Movimientoporlosmenus.html", "data-related": "[]"} },{ "id": "95598C9052C4433EAB2DC459E897102D", "parent" : "#", "text": "paradas", "a_attr": {"href": "Movimientoporlosmenus.html", "data-related": "[]"} },{ "id": "5AD3691BD55F4D1BB49AC6EA11A23882", "parent" : "#", "text": "Registrarse", "a_attr": {"href": "IniciarsesionoRegistrarse.html", "data-related": "[{\"title\":\"Iniciar sesion o Registrarse\",\"url\":\"IniciarsesionoRegistrarse.html\"},{\"title\":\"Movimiento por los menus\",\"url\":\"Movimientoporlosmenus.html\"}]"} }]